coinlib/BasicJob.py
coinlib/BasicJobSessionStorage.py
coinlib/ChartsFactory.py
coinlib/ChartsIndicatorJob.py
coinlib/ChartsWorker.py
coinlib/CoinlibCrypto.py
coinlib/CoinlibDataInterface.py
coinlib/CoinlibWorkspace.py
coinlib/DataWorker.py
coinlib/Functions.py
coinlib/InfluxDatabase.py
coinlib/PluginLoader.py
coinlib/PluginsWorker.py
coinlib/Registrar.py
coinlib/Simulator.py
coinlib/WorkerJobProcess.py
coinlib/__init__.py
coinlib/coinlibFactory.py
coinlib/config.py
coinlib/dataWorker_pb2.py
coinlib/dataWorker_pb2_grpc.py
coinlib/helper.py
coinlib/index.py
coinlib/logger.py
coinlib/broker/Broker.py
coinlib/broker/BrokerDTO.py
coinlib/broker/CoinlibBroker.py
coinlib/broker/CoinlibBrokerFuture.py
coinlib/broker/CoinlibBrokerMargin.py
coinlib/broker/CoinlibBrokerSpot.py
coinlib/broker/CoinlibSessionManager.py
coinlib/broker/__init__.py
coinlib/brokerWorker/BrokerFactory.py
coinlib/brokerWorker/BrokerSession.py
coinlib/brokerWorker/BrokerSessionWorker.py
coinlib/brokerWorker/BrokerWorker.py
coinlib/brokerWorker/TestProtocolResult.py
coinlib/brokerWorker/__init__.py
coinlib/data/CollectionInterface.py
coinlib/data/DataTable.py
coinlib/data/__init__.py
coinlib/drawable/CoinlibDrawable.py
coinlib/drawable/DrawableComponent.py
coinlib/drawable/WindowGrid.py
coinlib/drawable/__init__.py
coinlib/event/EventConsumer.py
coinlib/event/EventInterface.py
coinlib/event/__init__.py
coinlib/feature/CoinlibFeature.py
coinlib/feature/CoinlibFeatureFetcher.py
coinlib/feature/CoinlibFeatureLake.py
coinlib/feature/CoinlibFeatureProcessor.py
coinlib/feature/FeatureDTO.py
coinlib/feature/FeatureFactory.py
coinlib/feature/FeatureWorker.py
coinlib/feature/Features.py
coinlib/feature/__init__.py
coinlib/logics/Logic.py
coinlib/logics/LogicBasicWorker.py
coinlib/logics/LogicDTo.py
coinlib/logics/LogicJob.py
coinlib/logics/LogicLoader.py
coinlib/logics/LogicOfflineJob.py
coinlib/logics/LogicOfflineWorker.py
coinlib/logics/LogicOfflineWorkerData.py
coinlib/logics/LogicOfflineWorkerScreener.py
coinlib-2.3.0.dist-info/METADATA
coinlib-2.3.0.dist-info/WHEEL
coinlib-2.3.0.dist-info/entry_points.txt
coinlib-2.3.0.dist-info/top_level.txt
coinlib-2.3.0.dist-info/RECORD
