Metadata-Version: 2.1
Name: coinlib
Version: 2.3.0
Summary: Develop new code for your coindeck environment
Home-page: https://gitlab.com/coindeck/coinlib
Author: coindeck
Author-email: donnercody86@gmail.com
License: MIT
Classifier: License :: OSI Approved :: MIT License
Classifier: Programming Language :: Python
Classifier: Programming Language :: Python :: 2
Classifier: Programming Language :: Python :: 3
Requires-Dist: requests
Requires-Dist: ipython
Requires-Dist: ipykernel
Requires-Dist: semver
Requires-Dist: datascience
Requires-Dist: munch
Requires-Dist: packaging
Requires-Dist: coolname
Requires-Dist: google
Requires-Dist: aio-pika
Requires-Dist: grpcio
Requires-Dist: grpcio-tools
Requires-Dist: protobuf
Requires-Dist: cython
Requires-Dist: pandas
Requires-Dist: websocket-client
Requires-Dist: plotly
Requires-Dist: simplejson
Requires-Dist: ipynb-path
Requires-Dist: matplotlib
Requires-Dist: pyarrow
Requires-Dist: python-dateutil
Requires-Dist: chipmunkdb-python-client
Requires-Dist: pycryptodome
